{
  "swagger": "2.0",
  "info": {
    "title": "fastNotes",
    "description": "API documentation for fastNotes application",
    "version": "1.0.0"
  },
  "host": "localhost:8000",
  "basePath": "/api/v1/",
  "schemes": [
    "http"
  ],
  "paths": {
    "/auth/register": {
      "post": {
        "description": "",
        "parameters": [
          {
            "name": "body",
            "in": "body",
            "schema": {
              "type": "object",
              "properties": {
                "email": {
                  "example": "any"
                },
                "password": {
                  "example": "any"
                },
                "username": {
                  "example": "any"
                }
              }
            }
          }
        ],
        "responses": {
          "401": {
            "description": "Unauthorized"
          },
          "500": {
            "description": "Internal Server Error"
          }
        }
      }
    },
    "/auth/login": {
      "post": {
        "description": "",
        "parameters": [
          {
            "name": "body",
            "in": "body",
            "schema": {
              "type": "object",
              "properties": {
                "email": {
                  "example": "any"
                },
                "password": {
                  "example": "any"
                }
              }
            }
          }
        ],
        "responses": {
          "400": {
            "description": "Bad Request"
          },
          "401": {
            "description": "Unauthorized"
          },
          "500": {
            "description": "Internal Server Error"
          }
        }
      }
    },
    "/auth/logout": {
      "post": {
        "description": "",
        "responses": {
          "500": {
            "description": "Internal Server Error"
          }
        }
      }
    }
  }
}